{"name":"技术手册","postlist":[{"title":"markdown实用语法","slug":"Markdown实用语法","date":"2018-10-14T10:04:31.000Z","updated":"2022-06-02T01:05:59.614Z","comments":true,"path":"api/articles/Markdown实用语法.json","excerpt":null,"keywords":null,"cover":null,"content":null,"raw":null,"categories":[{"name":"技术手册","path":"api/categories/技术手册.json"}],"tags":[{"name":"markdown","path":"api/tags/markdown.json"}]},{"title":"hexo持续集成","slug":"hexo持续集成","date":"2019-01-04T03:04:49.000Z","updated":"2022-06-02T01:05:59.615Z","comments":true,"path":"api/articles/hexo持续集成.json","excerpt":null,"keywords":null,"cover":null,"content":null,"raw":null,"categories":[{"name":"技术手册","path":"api/categories/技术手册.json"}],"tags":[{"name":"hexo","path":"api/tags/hexo.json"}]},{"title":"vue项目实现CDN动静分离及自动化部署","slug":"vue项目实现CDN动静分离及自动化部署","date":"2022-03-02T09:32:33.000Z","updated":"2022-06-02T01:05:59.616Z","comments":true,"path":"api/articles/vue项目实现CDN动静分离及自动化部署.json","excerpt":null,"keywords":null,"cover":"https://imagecdn.bosong.online/pic/KtliwD.png","content":null,"raw":null,"categories":[{"name":"技术手册","path":"api/categories/技术手册.json"}],"tags":[{"name":"nginx","path":"api/tags/nginx.json"},{"name":"docker","path":"api/tags/docker.json"},{"name":"CDN","path":"api/tags/CDN.json"},{"name":"DEVOPS","path":"api/tags/DEVOPS.json"}]},{"title":"从github迁移到gitee和以coding为基础的的全链路devops","slug":"从github迁移到gitee和以coding为基础的的全链路devops","date":"2022-03-13T05:39:19.000Z","updated":"2022-06-02T01:05:59.616Z","comments":true,"path":"api/articles/从github迁移到gitee和以coding为基础的的全链路devops.json","excerpt":null,"keywords":null,"cover":"https://imagecdn.bosong.online/uPic/gitee-home_1647152067844.png","content":null,"raw":null,"categories":[{"name":"技术手册","path":"api/categories/技术手册.json"}],"tags":[{"name":"github","path":"api/tags/github.json"},{"name":"gitee","path":"api/tags/gitee.json"},{"name":"devops","path":"api/tags/devops.json"},{"name":"coding","path":"api/tags/coding.json"}]},{"title":"使用Authelia来实现多站的OIDC登录","slug":"使用Authelia来实现多站的OIDC登录","date":"2022-06-02T00:58:35.000Z","updated":"2022-06-02T01:05:59.617Z","comments":true,"path":"api/articles/使用Authelia来实现多站的OIDC登录.json","excerpt":null,"keywords":null,"cover":"https://imagecdn.bosong.online/uPic/61_1654131271466.jpeg","content":null,"raw":null,"categories":[{"name":"技术手册","path":"api/categories/技术手册.json"}],"tags":[{"name":"oidc","path":"api/tags/oidc.json"},{"name":"authelia","path":"api/tags/authelia.json"},{"name":"grafana","path":"api/tags/grafana.json"}]},{"title":"使用 SCF 自动刷新被 CDN 缓存的 COS 资源","slug":"使用SCF自动刷新被CDN缓存的COS资源","date":"2019-01-16T10:45:26.000Z","updated":"2022-06-02T01:05:59.617Z","comments":true,"path":"api/articles/使用SCF自动刷新被CDN缓存的COS资源.json","excerpt":null,"keywords":null,"cover":"https://imagecdn.bosong.online/image/332edc2828575a4c802a9af9cb233b08.png","content":null,"raw":null,"categories":[{"name":"技术手册","path":"api/categories/技术手册.json"}],"tags":[{"name":"cdn","path":"api/tags/cdn.json"}]},{"title":"好看又好用并且安全的密码管理工具","slug":"好看又好用并且安全的密码管理工具","date":"2020-10-09T15:51:10.000Z","updated":"2022-06-02T01:05:59.617Z","comments":true,"path":"api/articles/好看又好用并且安全的密码管理工具.json","excerpt":null,"keywords":null,"cover":null,"content":null,"raw":null,"categories":[{"name":"技术手册","path":"api/categories/技术手册.json"}],"tags":[{"name":"docker","path":"api/tags/docker.json"},{"name":"密码管理工具","path":"api/tags/密码管理工具.json"}]}]}